elasticgraph/__init__.py
elasticgraph/elasticgraph.py
elasticgraph/example.py
elasticgraph/d3js/.gitkeep
elasticgraph/d3js/__init__.py
elasticgraph/d3js/d3.v2.js
elasticgraph/d3js/d3graphscript.js
elasticgraph/d3js/index.html.j2
elasticgraph/d3js/styles.css
elasticgraph-0.2.0.dist-info/LICENSE
elasticgraph-0.2.0.dist-info/METADATA
elasticgraph-0.2.0.dist-info/NOTICE
elasticgraph-0.2.0.dist-info/WHEEL
elasticgraph-0.2.0.dist-info/top_level.txt
elasticgraph-0.2.0.dist-info/RECORD
