Metadata-Version: 2.1
Name: elasticgraph
Version: 0.2.0
Summary: Network Graph using D3js with grouping of nodes and elastic edges.
Home-page: https://gitlab.com/rwsdatalab/rwsdatalab/public/codebase/tools/elasticgraph
Author: RWS Datalab
Author-email: datalab.codebase@rws.nl
License: UNKNOWN
Keywords: elasticgraph
Platform: UNKNOWN
Classifier: Development Status :: 2 - Pre-Alpha
Classifier: Intended Audience :: Developers
Classifier: Natural Language :: English
Classifier: Programming Language :: Python :: 3
Classifier: Programming Language :: Python :: 3.8
Classifier: Programming Language :: Python :: 3.9
Classifier: Programming Language :: Python :: 3.10
Classifier: License :: OSI Approved
License-File: LICENSE
License-File: NOTICE
